MANIFEST.in
setup.py
./flask_extras/__init__.py
./flask_extras/decorators.py
./flask_extras/filters/__init__.py
./flask_extras/filters/config.py
./flask_extras/filters/filters.py
./flask_extras/filters/random.py
./flask_extras/macros/__init__.py
./flask_extras/views/__init__.py
./flask_extras/views/statuses.py
flask_extras/__init__.py
flask_extras/__init__.pyc
flask_extras/decorators.py
flask_extras/decorators.pyc
flask_extras.egg-info/PKG-INFO
flask_extras.egg-info/SOURCES.txt
flask_extras.egg-info/dependency_links.txt
flask_extras.egg-info/not-zip-safe
flask_extras.egg-info/requires.txt
flask_extras.egg-info/top_level.txt
flask_extras/__pycache__/__init__.cpython-35.pyc
flask_extras/filters/__init__.py
flask_extras/filters/__init__.pyc
flask_extras/filters/config.py
flask_extras/filters/config.pyc
flask_extras/filters/datetimes.py
flask_extras/filters/datetimes.pyc
flask_extras/filters/filters.py
flask_extras/filters/filters.pyc
flask_extras/filters/layout.py
flask_extras/filters/layout.pyc
flask_extras/filters/munging.py
flask_extras/filters/munging.pyc
flask_extras/filters/random.py
flask_extras/filters/random.pyc
flask_extras/filters/__pycache__/__init__.cpython-35.pyc
flask_extras/filters/__pycache__/config.cpython-35.pyc
flask_extras/filters/__pycache__/filters.cpython-35.pyc
flask_extras/filters/__pycache__/munging.cpython-35.pyc
flask_extras/filters/__pycache__/random.cpython-35.pyc
flask_extras/forms/__init__.py
flask_extras/forms/__init__.pyc
flask_extras/forms/wizard.py
flask_extras/forms/wizard.pyc
flask_extras/macros/__init__.py
flask_extras/macros/__init__.pyc
flask_extras/macros/bootstrap.html
flask_extras/macros/content_blocks.html
flask_extras/macros/dates.html
flask_extras/macros/extras_code.html
flask_extras/macros/extras_msg.html
flask_extras/macros/macros.html
flask_extras/macros/utils.html
flask_extras/macros/__pycache__/__init__.cpython-35.pyc
flask_extras/views/__init__.py
flask_extras/views/__init__.pyc
flask_extras/views/statuses.py
flask_extras/views/statuses.pyc