Metadata-Version: 1.1
Name: flask-extras
Version: 4.0.3
Summary: Assorted useful flask views, blueprints, Jinja2 template filters, and templates/macros
Home-page: https://github.com/christabor/flask_extras
Author: Chris Tabor
Author-email: dxdstudio@gmail.com
License: MIT
Platform: UNKNOWN
Classifier: Topic :: Software Development
Classifier: Programming Language :: Python :: 2.7
